fckr/__init__.py
fckr/fckr.py
fckr-1.1.dist-info/METADATA
fckr-1.1.dist-info/WHEEL
fckr-1.1.dist-info/entry_points.txt
fckr-1.1.dist-info/top_level.txt
fckr-1.1.dist-info/RECORD
