Metadata-Version: 2.4
Name: fckr
Version: 1.1
Summary: FCKR – The Ultimate Brute Forcer
Home-page: https://github.com/IMApurbo/fck
Author: AKM Korishee Apurbo
Author-email: bandinvisible8@gmail.com
License: MIT
Classifier: Programming Language :: Python :: 3
Classifier: License :: OSI Approved :: MIT License
Classifier: Operating System :: OS Independent
Requires-Python: >=3.7
Requires-Dist: requests>=2.25.1
Requires-Dist: rich>=13.3.5
Dynamic: author
Dynamic: author-email
Dynamic: classifier
Dynamic: description
Dynamic: description-content-type
Dynamic: home-page
Dynamic: license
Dynamic: requires-dist
Dynamic: requires-python
Dynamic: summary
